tabulartextmultimodalfusion/GridSearch.py
tabulartextmultimodalfusion/__init__.py
tabulartextmultimodalfusion/dataset.py
tabulartextmultimodalfusion/load_mimic.py
tabulartextmultimodalfusion/mimic_utils.py
tabulartextmultimodalfusion/models.py
tabulartextmultimodalfusion/optimization.py
tabulartextmultimodalfusion/settings.py
tabulartextmultimodalfusion-0.1.5.dist-info/LICENSE
tabulartextmultimodalfusion-0.1.5.dist-info/METADATA
tabulartextmultimodalfusion-0.1.5.dist-info/WHEEL
tabulartextmultimodalfusion-0.1.5.dist-info/top_level.txt
tabulartextmultimodalfusion-0.1.5.dist-info/RECORD
