Metadata-Version: 2.1
Name: tabulartextmultimodalfusion
Version: 0.1.5
Summary: A framework for multimodal fusion of tabular and text data.
Home-page: https://github.com/nadav22799/TabularTextMultimodalFusion
Author: Nadav Cohen
Author-email: nadav22799@gmail.com
Classifier: Programming Language :: Python :: 3
Classifier: License :: OSI Approved :: MIT License
Classifier: Operating System :: OS Independent
Requires-Python: >=3.8
License-File: LICENSE
Requires-Dist: torch-scatter >=2.1.0
Requires-Dist: torch-sparse >=0.6.0
Requires-Dist: torch-cluster >=1.6.0
Requires-Dist: torch-spline-conv >=1.2.0
Requires-Dist: torch-geometric >=2.4.0
